<?xml version="1.0" encoding="UTF-8"?>
<!DOCTYPE mapper PUBLIC "-//mybatis.org//DTD Mapper 3.0//EN" "http://mybatis.org/dtd/mybatis-3-mapper.dtd">
<mapper namespace="com.luffy.view.dao.OrderDao">
  <resultMap id="BaseResultMap" type="com.luffy.view.domain.Order">
    <id column="id" jdbcType="INTEGER" property="id" />
    <result column="order_id" jdbcType="INTEGER" property="orderId" />
    <result column="sku_id" jdbcType="INTEGER" property="skuId" />
    <result column="status" jdbcType="INTEGER" property="status" />
    <result column="ctime" jdbcType="TIMESTAMP" property="ctime" />
    <result column="mtime" jdbcType="TIMESTAMP" property="mtime" />
  </resultMap>
  <sql id="Example_Where_Clause">
    <where>
      <foreach collection="oredCriteria" item="criteria" separator="or">
        <if test="criteria.valid">
          <trim prefix="(" prefixOverrides="and" suffix=")">
            <foreach collection="criteria.criteria" item="criterion">
              <choose>
                <when test="criterion.noValue">
                  and ${criterion.condition}
                </when>
                <when test="criterion.singleValue">
                  and ${criterion.condition} #{criterion.value}
                </when>
                <when test="criterion.betweenValue">
                  and ${criterion.condition} #{criterion.value} and #{criterion.secondValue}
                </when>
                <when test="criterion.listValue">
                  and ${criterion.condition}
                  <foreach close=")" collection="criterion.value" item="listItem" open="(" separator=",">
                    #{listItem}
                  </foreach>
                </when>
              </choose>
            </foreach>
          </trim>
        </if>
      </foreach>
    </where>
  </sql>
  <sql id="Update_By_Example_Where_Clause">
    <where>
      <foreach collection="example.oredCriteria" item="criteria" separator="or">
        <if test="criteria.valid">
          <trim prefix="(" prefixOverrides="and" suffix=")">
            <foreach collection="criteria.criteria" item="criterion">
              <choose>
                <when test="criterion.noValue">
                  and ${criterion.condition}
                </when>
                <when test="criterion.singleValue">
                  and ${criterion.condition} #{criterion.value}
                </when>
                <when test="criterion.betweenValue">
                  and ${criterion.condition} #{criterion.value} and #{criterion.secondValue}
                </when>
                <when test="criterion.listValue">
                  and ${criterion.condition}
                  <foreach close=")" collection="criterion.value" item="listItem" open="(" separator=",">
                    #{listItem}
                  </foreach>
                </when>
              </choose>
            </foreach>
          </trim>
        </if>
      </foreach>
    </where>
  </sql>
  <sql id="Base_Column_List">
    id, order_id, sku_id, `status`, ctime, mtime
  </sql>
  <select id="selectByExample" parameterType="com.luffy.view.domain.OrderExample" resultMap="BaseResultMap">
    select
    <if test="distinct">
      distinct
    </if>
    <include refid="Base_Column_List" />
    from order_1
    <if test="_parameter != null">
      <include refid="Example_Where_Clause" />
    </if>
    <if test="orderByClause != null">
      order by ${orderByClause}
    </if>
    <if test="limit != null">
      <if test="offset != null">
        limit ${offset}, ${limit}
      </if>
      <if test="offset == null">
        limit ${limit}
      </if>
    </if>
  </select>
  <select id="selectByPrimaryKey" parameterType="java.lang.Integer" resultMap="BaseResultMap">
    select 
    <include refid="Base_Column_List" />
    from order_1
    where id = #{id,jdbcType=INTEGER}
  </select>
  <delete id="deleteByPrimaryKey" parameterType="java.lang.Integer">
    delete from order_1
    where id = #{id,jdbcType=INTEGER}
  </delete>
  <delete id="deleteByExample" parameterType="com.luffy.view.domain.OrderExample">
    delete from order_1
    <if test="_parameter != null">
      <include refid="Example_Where_Clause" />
    </if>
  </delete>
  <insert id="insert" parameterType="com.luffy.view.domain.Order">
    insert into order_1 (id, order_id, sku_id, 
      `status`, ctime, mtime
      )
    values (#{id,jdbcType=INTEGER}, #{orderId,jdbcType=INTEGER}, #{skuId,jdbcType=INTEGER}, 
      #{status,jdbcType=INTEGER}, #{ctime,jdbcType=TIMESTAMP}, #{mtime,jdbcType=TIMESTAMP}
      )
  </insert>
  <insert id="insertSelective" parameterType="com.luffy.view.domain.Order">
    insert into order_1
    <trim prefix="(" suffix=")" suffixOverrides=",">
      <if test="id != null">
        id,
      </if>
      <if test="orderId != null">
        order_id,
      </if>
      <if test="skuId != null">
        sku_id,
      </if>
      <if test="status != null">
        `status`,
      </if>
      <if test="ctime != null">
        ctime,
      </if>
      <if test="mtime != null">
        mtime,
      </if>
    </trim>
    <trim prefix="values (" suffix=")" suffixOverrides=",">
      <if test="id != null">
        #{id,jdbcType=INTEGER},
      </if>
      <if test="orderId != null">
        #{orderId,jdbcType=INTEGER},
      </if>
      <if test="skuId != null">
        #{skuId,jdbcType=INTEGER},
      </if>
      <if test="status != null">
        #{status,jdbcType=INTEGER},
      </if>
      <if test="ctime != null">
        #{ctime,jdbcType=TIMESTAMP},
      </if>
      <if test="mtime != null">
        #{mtime,jdbcType=TIMESTAMP},
      </if>
    </trim>
  </insert>
  <select id="countByExample" parameterType="com.luffy.view.domain.OrderExample" resultType="java.lang.Long">
    select count(*) from order_1
    <if test="_parameter != null">
      <include refid="Example_Where_Clause" />
    </if>
  </select>
  <update id="updateByExampleSelective" parameterType="map">
    update order_1
    <set>
      <if test="record.id != null">
        id = #{record.id,jdbcType=INTEGER},
      </if>
      <if test="record.orderId != null">
        order_id = #{record.orderId,jdbcType=INTEGER},
      </if>
      <if test="record.skuId != null">
        sku_id = #{record.skuId,jdbcType=INTEGER},
      </if>
      <if test="record.status != null">
        `status` = #{record.status,jdbcType=INTEGER},
      </if>
      <if test="record.ctime != null">
        ctime = #{record.ctime,jdbcType=TIMESTAMP},
      </if>
      <if test="record.mtime != null">
        mtime = #{record.mtime,jdbcType=TIMESTAMP},
      </if>
    </set>
    <if test="_parameter != null">
      <include refid="Update_By_Example_Where_Clause" />
    </if>
  </update>
  <update id="updateByExample" parameterType="map">
    update order_1
    set id = #{record.id,jdbcType=INTEGER},
      order_id = #{record.orderId,jdbcType=INTEGER},
      sku_id = #{record.skuId,jdbcType=INTEGER},
      `status` = #{record.status,jdbcType=INTEGER},
      ctime = #{record.ctime,jdbcType=TIMESTAMP},
      mtime = #{record.mtime,jdbcType=TIMESTAMP}
    <if test="_parameter != null">
      <include refid="Update_By_Example_Where_Clause" />
    </if>
  </update>
  <update id="updateByPrimaryKeySelective" parameterType="com.luffy.view.domain.Order">
    update order_1
    <set>
      <if test="orderId != null">
        order_id = #{orderId,jdbcType=INTEGER},
      </if>
      <if test="skuId != null">
        sku_id = #{skuId,jdbcType=INTEGER},
      </if>
      <if test="status != null">
        `status` = #{status,jdbcType=INTEGER},
      </if>
      <if test="ctime != null">
        ctime = #{ctime,jdbcType=TIMESTAMP},
      </if>
      <if test="mtime != null">
        mtime = #{mtime,jdbcType=TIMESTAMP},
      </if>
    </set>
    where id = #{id,jdbcType=INTEGER}
  </update>
  <update id="updateByPrimaryKey" parameterType="com.luffy.view.domain.Order">
    update order_1
    set order_id = #{orderId,jdbcType=INTEGER},
      sku_id = #{skuId,jdbcType=INTEGER},
      `status` = #{status,jdbcType=INTEGER},
      ctime = #{ctime,jdbcType=TIMESTAMP},
      mtime = #{mtime,jdbcType=TIMESTAMP}
    where id = #{id,jdbcType=INTEGER}
  </update>
</mapper>